fastrates_cli/__init__.py
fastrates_cli/__main__.py
fastrates_cli/main.py
fastrates_cli-0.1.1.dist-info/entry_points.txt
fastrates_cli-0.1.1.dist-info/WHEEL
fastrates_cli-0.1.1.dist-info/METADATA
fastrates_cli-0.1.1.dist-info/RECORD
